voidpy/__init__.py
voidpy/api.py
voidpy/cli.py
voidpy/cor.py
voidpy/crp.py
voidpy/enc.py
voidpy/prs.py
voidpy/run.py
voidpy/stm.py
voidpy/vm.py
voidpy-1.0.1.dist-info/licenses/LICENSE
voidpy-1.0.1.dist-info/METADATA
voidpy-1.0.1.dist-info/WHEEL
voidpy-1.0.1.dist-info/entry_points.txt
voidpy-1.0.1.dist-info/top_level.txt
voidpy-1.0.1.dist-info/RECORD
