Metadata-Version: 2.4
Name: voidpy
Version: 1.0.1
Summary: Void Execution Engine - Translates Python to Logic States
Home-page: https://github.com/MERO/voidpy
Author: MERO
Author-email: MERO <mero@voidpy.dev>
Maintainer: MERO
License: MIT
Project-URL: Homepage, https://github.com/MERO/voidpy
Project-URL: Documentation, https://github.com/MERO/voidpy#readme
Project-URL: Repository, https://github.com/MERO/voidpy
Project-URL: Telegram, https://t.me/QP4RM
Keywords: encryption,obfuscation,bytecode,void,logic-states,protection
Classifier: Development Status :: 5 - Production/Stable
Classifier: Intended Audience :: Developers
Classifier: License :: OSI Approved :: MIT License
Classifier: Operating System :: OS Independent
Classifier: Programming Language :: Python :: 3
Classifier: Programming Language :: Python :: 3.6
Classifier: Programming Language :: Python :: 3.7
Classifier: Programming Language :: Python :: 3.8
Classifier: Programming Language :: Python :: 3.9
Classifier: Programming Language :: Python :: 3.10
Classifier: Programming Language :: Python :: 3.11
Classifier: Programming Language :: Python :: 3.12
Classifier: Programming Language :: Python :: 3.13
Classifier: Topic :: Security :: Cryptography
Classifier: Topic :: Software Development :: Code Generators
Requires-Python: >=3.6
License-File: LICENSE
Dynamic: author
Dynamic: home-page
Dynamic: license-file
Dynamic: requires-python
